clean_actions/__init__.py
clean_actions/__main__.py
clean_actions/api.py
clean_actions/clean.py
clean_actions/cli.py
clean_actions/yaml.py
clean_actions/features/cleanup_commands.py
clean_actions/features/commands.py
clean_actions/features/global_run_as.py
clean_actions/features/strip_x_prefixed_root_tags.py
clean_actions-0.1.0.dist-info/LICENSE
clean_actions-0.1.0.dist-info/WHEEL
clean_actions-0.1.0.dist-info/METADATA
clean_actions-0.1.0.dist-info/RECORD
